{
    "image_path": "",
    "qa_pairs": [
        {
            "question_type": "detailed_explanation",
            "question": "這張圖片中的元素與這個景點的特色有何關係?",
            "answer": "這張圖片中的元素，包括女孩站在窗邊、穿著藍色的連衣裙、周圍有幾個人正在聚集、背景有綠樹、窗戶透進自然光、屋內裝飾有雲朵造型的裝飾物，營造出一種輕鬆的氛圍。這些元素與921地震教育園區的特色不太匹配。921地震教育園區主要是展示地震相關的教育和紀念設施，通常有高科技的展覽、模擬地震設施以及紀念碑等，而不是主要以人群聚集和模特為主的場景。"
        },
        {
            "question_type": "complex_reasoning",
            "question": "這個景點在當地的文化和歷史中扮演了什麼樣的角色？",
            "answer": "921地震教育園區是國立自然科學博物館設在臺中市霧峰區光復新村的地震博物館，全館座落地震遺址之上，沿斷層而建，以充滿特色的建築與遺址做藝術化的結合；並將部分地震後留下的毀壞教室、斷層剖面完好如初地作為教材展示，教室進行結構性補強。展示內容包括地震科學、地震體驗與防災教育，做為以後專家研究跟教學使用，及幫助大眾建立正確的地震防災觀念。"
        }
    ]
}