{
    "image_path": "input_image/台北小巨蛋/台北小巨蛋-37.jpg",
    "qa_pairs": [
        {
            "question_type": "detailed_description",
            "question": "請詳細描述圖片中的台灣景點的視覺特徵、歷史背景和文化意義。",
            "answer": "這張圖片中的建築是高雄的一個知名地標，高雄市的高雄巨蛋。它的建築設計融合了現代化與動感曲線，外觀上採用大片的玻璃帷幕，給人一種透明而開放的感覺。屋頂呈曲線形，類似於一個巨大的貝殼，用以提升視覺上的動感。\n\n### 視覺特徵\n- **玻璃帷幕**：使建築外觀具有現代感，並可以自然光穿透進入內部。\n- **曲線設計**：整體設計流暢而具有動感，屋頂的弧形結構讓人聯想到海浪。\n- **大面積**：適合舉行大型活動，體現其多功能的用途。\n\n### 歷史背景\n高雄巨蛋的建成目的是為了加強高雄作為台灣南部重要城市的文化與經濟地位。自啟用以來，它成為舉辦各類音樂會、體育賽事和展覽的重要場所。\n\n### 文化意義\n除了是一個重要的商業和娛樂場所，它還象徵著高雄這座城市蓬勃的發展和現代化方向。透過這些活動，巨蛋成為促進文化交流和社會聚集的重要平台。\n\n高雄巨蛋的建築設計和其在城市中的角色，反映出高雄市從傳統港口城市向現代多元城市轉型的努力。"
        },
        {
            "question_type": "detailed_description",
            "question": "圖片中的這個景點有哪些著名的地標或建築？它們有什麼特殊之處？",
            "answer": "這張圖片是台北的小巨蛋，也稱為台北巨蛋或台北小巨蛋。這是一座多功能體育館，主要用於音樂會、運動賽事和各類大型活動。它以其現代化的外觀和先進的設施而聞名，能夠容納萬人以上的觀眾。\n\n台北小巨蛋的特殊之處在於：\n\n1. **設計現代**：其橢圓形的建築結構代表了現代建築技術的頂峰。\n2. **多用途功能**：內部裝有高科技舞台設備和靈活的場地配置，可以根據不同活動進行調整。\n3. **交通便利**：位於市中心，鄰近地鐵和公共交通設施，讓參加活動的觀眾能夠方便地抵達。\n\n這座地標是台北吸引國際音樂人和文體活動的重要場地之一。"
        }
    ]
}