{
    "image_path": "",
    "qa_pairs": [
        {
            "question_type": "detailed_explanation",
            "question": "這張圖片顯示了一條鋸齒狀走道，走道上投射著過去的照片，可能是展示歷史事件或故事。",
            "answer": "這條鋸齒狀走道可能是展示歷史事件或故事的走道，走道上投射著過去的照片，讓人們可以通過這條走道來體驗和了解歷史事件或故事。"
        },
        {
            "question_type": "detailed_explanation",
            "question": "圖片中可見幾位遊客正在走動，背景似乎是室內空間，可能是展覽中心的一部分。",
            "answer": "圖片中可見幾位遊客正在走動，背景似乎是室內空間，可能是展覽中心的一部分，展覽中心可能是展示歷史事件或故事的場所，讓人們可以通過這條走道來體驗和了解歷史事件或故事。"
        },
        {
            "question_type": "detailed_explanation",
            "question": "投射的照片內容不明，但通常這些展示會包含地震相關的歷史瞬間和人們的生活。",
            "answer": "投射的照片內容不明，但通常這些展示會包含地震相關的歷史瞬間和人們的生活，讓人們可以通過這些照片來了解地震的歷史和影響。"
        },
        {
            "question_type": "complex_reasoning",
            "question": "這個景點在當地的文化和歷史中扮演了什麼樣的角色？",
            "answer": "921地震教育園區是國立自然科學博物館設在臺中市霧峰區光復新村的地震博物館，展示歷史事件、地震的影響和防災教育。"
        }
    ]
}