{
    "image_path": "",
    "qa_pairs": [
        {
            "question_type": "detailed_explanation",
            "question": "這張圖片中的元素與哪個景點最相匹配?",
            "answer": "這張圖片中的元素與921地震教育園區最相匹配。921地震教育園區是一個地震博物館，主要用於教育和記憶921地震的影響。園區內有多個展館，包括車籠埔斷層保存館、地震工程教育館、影像館、防災教育館和重建記錄館。這些展館展示了921地震的歷史、地震科學、地震體驗和防災教育等多個方面。"
        },
        {
            "question_type": "detailed_explanation",
            "question": "這個景點的特色是什麼?",
            "answer": "這個景點的特色包括展示921地震的歷史、地震科學、地震體驗和防災教育等多個方面。園區內的各個展館都提供了不同的教育和體驗機會，使參觀者可以深入了解921地震的影響和教訓。"
        },
        {
            "question_type": "complex_reasoning",
            "question": "這個景點在當地的文化和歷史中扮演了什麼樣的角色？",
            "answer": "921地震教育園區是一個以教育和記憶921地震的影響為主題的博物館，位於臺中市霧峰區光復新村，展示了地震科學、地震體驗和防災教育。它是國立自然科學博物館的一部分，主要用於教育和研究。"
        }
    ]
}